{
  "TunerTutorials": {
    "TEXT": [
      "게임 개발부에서 이상한 게임을 하고 나서, 선도부장님이 깨어나지 못하고 있습니다!! 인정하고 싶지 않지만, 게헨나 학원 학생회는 선도부장님을 깨우기 위해 당신이 필요합니다. 이제 선생님이 선도부장님을 이해하도록 돕겠습니다.",
      "선도부장님은 #y뽑을 #y카드 #y더미의 상위 5장을 볼 수 있습니다. 히나 선도부장의 많은 카드들이 이러한 \"목표\"와 상호작용할 수 있습니다.",
      "선도부장님의 신비는 선생님의 관점에서 #y엘레프로 변합니다. 전투 시작 시, #y엘레프들은 선도부장님의 무기에 채워집니다. 각 전투 승리 후, 선생님은 새로운 #y엘레프 1개를 획득할 수 있습니다.",
      "위의 정보는 #y디스트로이어에 기록되어 있으며, 선생님은 언제든지 확인할 수 있습니다. 나머지는 선생님께 맡기겠습니다."
    ],
    "LABEL": [
      "선생님!!!!",
      "목표 보기",
      "엘레프들",
      ""
    ]
  },
  "TunerREADME": {
    "TEXT": [
      "게헨나 학원 선도부의 부장. 평소에는 거의 모든 것을 귀찮아하는 나태한 소녀이지만, 규칙과 규정을 다룰 때는 여전히 엄격한 선도부장입니다."
    ],
    "LABEL": [
      "히나"
    ]
  },
  "TunerBeforeDead": {
    "TEXT": [
      "귀찮아..."
    ],
    "LABEL": [
      "심장 대사"
    ]
  },
  "TunerFullArtTutorial": {
    "TEXT": [
      "Full Art Card"
    ],
    "LABEL": [
      "The card has small stars on the bottom right corner. You can right-click these cards anywhere to flip them and switch to the full art card."
    ]
  }
}
